[
    {
        "symbol": "DAI",
        "name": "Dai Stablecoin",
        "address": "0xcB1e72786A6eb3b44C2a2429e317c8a2462CFeb1",
        "decimals": 18,
        "chainId": 80001,
        "logoURI": "https://elk.finance/tokens/logos/mumbai/0xcB1e72786A6eb3b44C2a2429e317c8a2462CFeb1/logo.png",
        "coingeckoId": null,
        "listedIn": [
            "sushiswap",
            "elkfinance"
        ]
    },
    {
        "symbol": "ETH",
        "name": "Ether",
        "address": "0x714550C2C1Ea08688607D86ed8EeF4f5E4F22323",
        "decimals": 18,
        "chainId": 80001,
        "logoURI": "https://elk.finance/tokens/logos/mumbai/0x714550C2C1Ea08688607D86ed8EeF4f5E4F22323/logo.png",
        "coingeckoId": null,
        "listedIn": [
            "sushiswap",
            "elkfinance"
        ]
    },
    {
        "symbol": "USDT",
        "name": "Tether USD",
        "address": "0x3813e82e6f7098b9583FC0F33a962D02018B6803",
        "decimals": 6,
        "chainId": 80001,
        "logoURI": "https://elk.finance/tokens/logos/mumbai/0x3813e82e6f7098b9583FC0F33a962D02018B6803/logo.png",
        "coingeckoId": null,
        "listedIn": [
            "sushiswap",
            "elkfinance"
        ]
    }
]